PyListFunctions/SCRAPPED_type_list_class.py
PyListFunctions/__init__.py
PyListFunctions/__init__.pyi
PyListFunctions/classes.py
PyListFunctions/classes.pyi
PyListFunctions/list_func_part.py
PyListFunctions/list_func_part_scrapped_code.py
PyListFunctions/str_func_part.py
PyListFunctions/advanced_list_EXTRA/__init__.py
PyListFunctions/advanced_list_EXTRA/initialization.py
PyListFunctions/advanced_list_EXTRA/lock_part.py
PyListFunctions/advanced_list_EXTRA/other_func_part.py
PyListFunctions/advanced_list_EXTRA/reservation_part.py
PyListFunctions/advanced_list_EXTRA/scrapped code.py
PyListFunctions/advanced_list_EXTRA/type_part.py
PyListFunctions/advanced_list_EXTRA_OLD/__init__.py
PyListFunctions/advanced_list_MAIN/lock_part.py
PyListFunctions/advanced_list_MAIN/other_method_part.py
PyListFunctions/advanced_list_MAIN/reservation_part.py
PyListFunctions/advanced_list_MAIN/type_part.py
PyListFunctions/advanced_list_MAIN_OLD/__init__.py
PyListFunctions/limit_len_list/__init__.py
PyListFunctions-0.9.3.dist-info/METADATA
PyListFunctions-0.9.3.dist-info/WHEEL
PyListFunctions-0.9.3.dist-info/top_level.txt
PyListFunctions-0.9.3.dist-info/RECORD
