Metadata-Version: 2.1
Name: PyListFunctions
Version: 0.9.3
Summary: some functions(include decorators) and classes for list (and some other kinds of functions)
Home-page: https://space.bilibili.com/1654383134
Author: BL_30G(BiliBili现名为:NPC-013)
Author-email: 2842621898@qq.com
License: UNKNOWN
Keywords: python,list,clean,functions,string,bool,class,type
Platform: UNKNOWN
Classifier: Development Status :: 3 - Alpha
Classifier: Intended Audience :: Developers
Classifier: Topic :: Utilities
Classifier: License :: OSI Approved :: MIT License
Classifier: Programming Language :: Python :: 3.7
Classifier: Programming Language :: Python :: 3.8
Classifier: Programming Language :: Python :: 3.9
Classifier: Programming Language :: Python :: 3.10
Classifier: Programming Language :: Python :: 3.11
Classifier: Programming Language :: Python :: 3.12
Classifier: Programming Language :: Python :: 3.13
Classifier: Programming Language :: Python :: 3.14
